airss_baseline/__init__.py
airss_baseline/calculators.py
airss_baseline/run_airss_generation.py
airss_baseline/run_hot_airss_generation.py
airss_baseline/utils.py
energy_model/__init__.py
energy_model/diffusion_tools.py
energy_model/training_tools.py
moldiff/__init__.py
moldiff/analysis.py
moldiff/atoms_cleanup.py
moldiff/calculators.py
moldiff/diffusion_tools.py
moldiff/element_swapping.py
moldiff/generation_utils.py
moldiff/hydrogenation.py
moldiff/hydrogenation_deterministic.py
moldiff/integrators.py
moldiff/manifolds.py
moldiff/parallel_relaxation.py
moldiff/particle_filtering.py
moldiff/sampling.py
moldiff/temperature_annealing.py
moldiff/utils.py
moldiff/zndraw.py
moldiff_server/__init__.py
moldiff_server/cli.py
moldiff_server/data.py
moldiff_server/endpoints.py
moldiff_server/main.py
moldiff_server/ray_app.py
moldiff_server/utils.py
moldiff_zndraw/__init__.py
moldiff_zndraw/cli.py
moldiff_zndraw/data.py
moldiff_zndraw/endpoints.py
moldiff_zndraw/host_model.py
moldiff_zndraw/local_server.py
moldiff_zndraw/main.py
moldiff_zndraw/ray_app.py
moldiff_zndraw/setup_defaults.py
moldiff_zndraw/utils.py
simgen/__init__.py
simgen/analysis.py
simgen/atoms_cleanup.py
simgen/calculators.py
simgen/element_swapping.py
simgen/generation_utils.py
simgen/hydrogenation.py
simgen/hydrogenation_deterministic.py
simgen/integrators.py
simgen/manifolds.py
simgen/particle_filtering.py
simgen/sascrorer.py
simgen/temperature_annealing.py
simgen/utils.py
simgen_zndraw/__init__.py
simgen_zndraw/cli.py
simgen_zndraw/data.py
simgen_zndraw/endpoints.py
simgen_zndraw/local_server.py
simgen_zndraw/main.py
simgen_zndraw/utils.py
simgen-0.2.2.dist-info/LICENSE
simgen-0.2.2.dist-info/METADATA
simgen-0.2.2.dist-info/WHEEL
simgen-0.2.2.dist-info/entry_points.txt
simgen-0.2.2.dist-info/top_level.txt
simgen-0.2.2.dist-info/RECORD
