Metadata-Version: 2.1
Name: simgen
Version: 0.2.2
Author-email: Rokas Elijošius <re344@cam.ac.uk>
License: MIT License
Requires-Python: >=3.10
License-File: LICENSE
Requires-Dist: ase>=3.23
Requires-Dist: einops>=0.6.1
Requires-Dist: fire>=0.5.0
Requires-Dist: frozendict>=2.3.7
Requires-Dist: typer>=0.13
Requires-Dist: decorator
Requires-Dist: mace-models>=0.1.2
Requires-Dist: mace-torch>=0.3.9
Requires-Dist: hydromace>=0.2
Requires-Dist: znframe
Requires-Dist: zndraw>=0.5.7
Provides-Extra: all
Requires-Dist: rdkit>=2023.9.4; extra == "all"
